{    
    "any":{
        "name":"Tout anneau"
    },
    "earth":{
        "name":"Terre",
        "approachNames":{
            "artisan":"Restaurer",
            "social":"Raisonner",
            "scholar":"Se remémorer",
            "martial":"Résister",
            "trade":"Produire"
        }
    },    
    "water":{
        "name":"Eau",
        "approachNames":{
            "artisan":"Adapter",
            "social":"Charmer",
            "scholar":"Observer",
            "martial":"Détourner",
            "trade":"Échanger"
        }
    },
    "fire":{
        "name":"Feu",
        "approachNames":{
            "artisan":"Inventer",
            "social":"Inciter",
            "scholar":"Théoriser",
            "martial":"Submerger",
            "trade":"Innover"
        }
    },
    "air":{
        "name":"Air",
        "approachNames":{
            "artisan":"Raffiner",
            "social":"Duper",
            "scholar":"Analyser",
            "martial":"Feinter",
            "trade":"Escroquer"
        }
    },
    "void":{
        "name":"Vide",
        "approachNames":{
            "artisan":"S’harmoniser",
            "social":"Illuminer",
            "scholar":"Ressentir",
            "martial":"Lâcher prise",
            "trade":"Subsister"
        }
    }
}